awe/__init__.py
awe/awe.py
awe/oss.py
awe/clients/comfyui_client.py
awe/mq/mq_listener.py
awe/mq/mq_producer.py
awe/types/common.py
awe/util/comfyui_exception.py
awe/util/http.py
awe/util/logging.py
awe/util/tongyi.py
awe/util/util.py
awe/util/workflow.py
malette_awe-0.1.14.dist-info/METADATA
malette_awe-0.1.14.dist-info/WHEEL
malette_awe-0.1.14.dist-info/top_level.txt
malette_awe-0.1.14.dist-info/RECORD
