Metadata-Version: 2.4
Name: malette-awe
Version: 0.1.14
Summary: AWE
Author-email: jinchan <mark.chengke@qq.com>
Project-URL: Homepage, https://github.com/maletteAI/awe
Project-URL: Issues, https://github.com/maletteAI/awe/issues
Classifier: Programming Language :: Python :: 3
Classifier: License :: OSI Approved :: GNU Affero General Public License v3
Classifier: Operating System :: OS Independent
Requires-Python: >=3.7
Requires-Dist: uvicorn
Requires-Dist: pillow
Requires-Dist: requests
Requires-Dist: typing
Requires-Dist: fastapi
Requires-Dist: pydantic
Requires-Dist: mq_http_sdk
Requires-Dist: tenacity
Requires-Dist: oss2
Requires-Dist: nanoid
Requires-Dist: dashscope
Requires-Dist: piexif
Requires-Dist: websocket-client
Requires-Dist: replicate
Requires-Dist: redis
Requires-Dist: python-dotenv
Provides-Extra: test
Requires-Dist: pytest>=7.0; extra == "test"
Requires-Dist: pytest-cov>=4.0; extra == "test"
Requires-Dist: pytest-mock>=3.10; extra == "test"
